directory_bootstrap/__init__.py
directory_bootstrap/__main__.py
directory_bootstrap/setup.py
directory_bootstrap/distros/__init__.py
directory_bootstrap/distros/alpine.py
directory_bootstrap/distros/arch.py
directory_bootstrap/distros/base.py
directory_bootstrap/distros/gentoo.py
directory_bootstrap/distros/void.py
directory_bootstrap/resources/__init__.py
directory_bootstrap/resources/alpine/__init__.py
directory_bootstrap/resources/alpine/ncopa.asc
directory_bootstrap/resources/gentoo/13EBBDBEDE7A12775DFDB1BABB572E0E2D182910.asc
directory_bootstrap/resources/gentoo/18F703D702B1B9591373148C55D3238EC050396E.asc
directory_bootstrap/resources/gentoo/2C13823B8237310FA213034930D132FF0FF50EEB.asc
directory_bootstrap/resources/gentoo/ABD00913019D6354BA1D9A132839FE0D796198B1.asc
directory_bootstrap/resources/gentoo/D99EAC7379A850BCE47DA5F29E6438C817072058.asc
directory_bootstrap/resources/gentoo/DCD05B71EAB94199527F44ACDB6B8C1F96D8BF6D.asc
directory_bootstrap/resources/gentoo/EF9538C9E8E64311A52CDEDFA13D0EF1914E7A72.asc
directory_bootstrap/resources/gentoo/__init__.py
directory_bootstrap/shared/__init__.py
directory_bootstrap/shared/byte_size.py
directory_bootstrap/shared/commands.py
directory_bootstrap/shared/executor.py
directory_bootstrap/shared/messenger.py
directory_bootstrap/shared/metadata.py
directory_bootstrap/shared/mount.py
directory_bootstrap/shared/namespace.py
directory_bootstrap/shared/output_control.py
directory_bootstrap/shared/resolv_conf.py
directory_bootstrap/shared/loaders/__init__.py
directory_bootstrap/shared/loaders/_argparse.py
directory_bootstrap/shared/loaders/_bs4.py
directory_bootstrap/shared/loaders/_colorama.py
directory_bootstrap/shared/loaders/_requests.py
directory_bootstrap/tools/__init__.py
directory_bootstrap/tools/stage3_latest_parser.py
image_bootstrap/__init__.py
image_bootstrap/__main__.py
image_bootstrap/engine.py
image_bootstrap/mount.py
image_bootstrap/boot_loaders/__init__.py
image_bootstrap/boot_loaders/grub2.py
image_bootstrap-3.0.0.dist-info/METADATA
image_bootstrap-3.0.0.dist-info/WHEEL
image_bootstrap-3.0.0.dist-info/entry_points.txt
image_bootstrap-3.0.0.dist-info/top_level.txt
image_bootstrap-3.0.0.dist-info/RECORD
